{"Entities": [{"Id": 0, "BeginOffset": 31, "EndOffset": 41, "Score": 0.27098649740219116, "Text": "withdrawal", "Category": "MEDICAL_CONDITION", "Type": "DX_NAME", "Traits": []}], "UnmappedAttributes": [], "ResponseMetadata": {"RequestId": "f85b1e6d-044b-11e9-87ba-b11501cb146b", "HTTPStatusCode": 200, "HTTPHeaders": {"content-type": "application/x-amz-json-1.1", "date": "Thu, 20 Dec 2018 11:39:53 GMT", "x-amzn-requestid": "f85b1e6d-044b-11e9-87ba-b11501cb146b", "content-length": "187", "connection": "keep-alive"}, "RetryAttempts": 1}}