{"Entities": [{"Id": 0, "BeginOffset": 10, "EndOffset": 24, "Score": 0.7925928831100464, "Text": "blood pressure", "Category": "TEST_TREATMENT_PROCEDURE", "Type": "TEST_NAME", "Traits": []}], "UnmappedAttributes": [], "ResponseMetadata": {"RequestId": "6bbaf1e3-044c-11e9-9cad-8715dd21eb24", "HTTPStatusCode": 200, "HTTPHeaders": {"content-type": "application/x-amz-json-1.1", "date": "Thu, 20 Dec 2018 11:43:07 GMT", "x-amzn-requestid": "6bbaf1e3-044c-11e9-9cad-8715dd21eb24", "content-length": "199", "connection": "keep-alive"}, "RetryAttempts": 0}}