{"Entities": [{"Id": 0, "BeginOffset": 0, "EndOffset": 12, "Score": 0.9900480508804321, "Text": "constipation", "Category": "MEDICAL_CONDITION", "Type": "DX_NAME", "Traits": [{"Name": "DIAGNOSIS", "Score": 0.4261336326599121}]}, {"Id": 1, "BeginOffset": 13, "EndOffset": 21, "Score": 0.4047848880290985, "Text": "x 1 week", "Category": "MEDICAL_CONDITION", "Type": "ACUITY", "Traits": []}], "UnmappedAttributes": [], "ResponseMetadata": {"RequestId": "bfee93f5-044c-11e9-9cad-8715dd21eb24", "HTTPStatusCode": 200, "HTTPHeaders": {"content-type": "application/x-amz-json-1.1", "date": "Thu, 20 Dec 2018 11:45:29 GMT", "x-amzn-requestid": "bfee93f5-044c-11e9-9cad-8715dd21eb24", "content-length": "379", "connection": "keep-alive"}, "RetryAttempts": 0}}