{"Entities": [{"Id": 0, "BeginOffset": 0, "EndOffset": 20, "Score": 0.9337565898895264, "Text": "difficulty breathing", "Category": "MEDICAL_CONDITION", "Type": "DX_NAME", "Traits": [{"Name": "SYMPTOM", "Score": 0.7158017754554749}]}], "UnmappedAttributes": [], "ResponseMetadata": {"RequestId": "e0826bd3-044c-11e9-be2d-0757d81fd362", "HTTPStatusCode": 200, "HTTPHeaders": {"content-type": "application/x-amz-json-1.1", "date": "Thu, 20 Dec 2018 11:46:24 GMT", "x-amzn-requestid": "e0826bd3-044c-11e9-be2d-0757d81fd362", "content-length": "240", "connection": "keep-alive"}, "RetryAttempts": 0}}