{"Entities": [{"Id": 0, "BeginOffset": 8, "EndOffset": 16, "Score": 0.9977856874465942, "Text": "diarrhea", "Category": "MEDICAL_CONDITION", "Type": "DX_NAME", "Traits": [{"Name": "SYMPTOM", "Score": 0.648740291595459}]}, {"Id": 1, "BeginOffset": 21, "EndOffset": 26, "Score": 0.9838682413101196, "Text": "fever", "Category": "MEDICAL_CONDITION", "Type": "DX_NAME", "Traits": [{"Name": "SYMPTOM", "Score": 0.4814113974571228}]}], "UnmappedAttributes": [], "ResponseMetadata": {"RequestId": "6ccae8f6-0451-11e9-b08d-7f5a50b8bedb", "HTTPStatusCode": 200, "HTTPHeaders": {"content-type": "application/x-amz-json-1.1", "date": "Thu, 20 Dec 2018 12:18:56 GMT", "x-amzn-requestid": "6ccae8f6-0451-11e9-b08d-7f5a50b8bedb", "content-length": "415", "connection": "keep-alive"}, "RetryAttempts": 0}}