{"Entities": [{"Id": 0, "BeginOffset": 0, "EndOffset": 2, "Score": 0.9822973012924194, "Text": "lt", "Category": "ANATOMY", "Type": "DIRECTION", "Traits": []}, {"Id": 1, "BeginOffset": 3, "EndOffset": 7, "Score": 0.9715471267700195, "Text": "knee", "Category": "ANATOMY", "Type": "SYSTEM_ORGAN_SITE", "Traits": []}], "UnmappedAttributes": [], "ResponseMetadata": {"RequestId": "ca046b2e-0451-11e9-b44d-5771a9e0fee9", "HTTPStatusCode": 200, "HTTPHeaders": {"content-type": "application/x-amz-json-1.1", "date": "Thu, 20 Dec 2018 12:21:34 GMT", "x-amzn-requestid": "ca046b2e-0451-11e9-b44d-5771a9e0fee9", "content-length": "308", "connection": "keep-alive"}, "RetryAttempts": 0}}