{"Entities": [{"Id": 2, "BeginOffset": 29, "EndOffset": 49, "Score": 0.5218928456306458, "Text": "spontaneous abortion", "Category": "MEDICAL_CONDITION", "Type": "DX_NAME", "Traits": [{"Name": "DIAGNOSIS", "Score": 0.826529324054718}]}, {"Id": 0, "BeginOffset": 71, "EndOffset": 82, "Score": 0.3070272207260132, "Text": "pregcy test", "Category": "TEST_TREATMENT_PROCEDURE", "Type": "TEST_NAME", "Traits": [], "Attributes": [{"Type": "TEST_VALUE", "Score": 0.5443352460861206, "RelationshipScore": 0.9999964237213135, "Id": 1, "BeginOffset": 83, "EndOffset": 91, "Text": "positive", "Traits": []}]}], "UnmappedAttributes": [], "ResponseMetadata": {"RequestId": "f637930c-0451-11e9-87ba-b11501cb146b", "HTTPStatusCode": 200, "HTTPHeaders": {"content-type": "application/x-amz-json-1.1", "date": "Thu, 20 Dec 2018 12:22:48 GMT", "x-amzn-requestid": "f637930c-0451-11e9-87ba-b11501cb146b", "content-length": "572", "connection": "keep-alive"}, "RetryAttempts": 1}}