{"Entities": [{"Id": 0, "BeginOffset": 4, "EndOffset": 18, "Score": 0.804908037185669, "Text": "abdominal pain", "Category": "MEDICAL_CONDITION", "Type": "DX_NAME", "Traits": [{"Name": "SYMPTOM", "Score": 0.8311405777931213}]}], "UnmappedAttributes": [], "ResponseMetadata": {"RequestId": "4ac3672a-0452-11e9-be2d-0757d81fd362", "HTTPStatusCode": 200, "HTTPHeaders": {"content-type": "application/x-amz-json-1.1", "date": "Thu, 20 Dec 2018 12:25:10 GMT", "x-amzn-requestid": "4ac3672a-0452-11e9-be2d-0757d81fd362", "content-length": "233", "connection": "keep-alive"}, "RetryAttempts": 0}}