{"Entities": [{"Id": 4, "BeginOffset": 0, "EndOffset": 5, "Score": 0.9813421368598938, "Text": "chest", "Category": "ANATOMY", "Type": "SYSTEM_ORGAN_SITE", "Traits": []}, {"Id": 1, "BeginOffset": 0, "EndOffset": 10, "Score": 0.8332185745239258, "Text": "chest pain", "Category": "MEDICAL_CONDITION", "Type": "DX_NAME", "Traits": [{"Name": "SYMPTOM", "Score": 0.44742313027381897}]}, {"Id": 0, "BeginOffset": 11, "EndOffset": 16, "Score": 0.4983322322368622, "Text": "i2699", "Category": "PROTECTED_HEALTH_INFORMATION", "Type": "ID", "Traits": []}, {"Id": 2, "BeginOffset": 23, "EndOffset": 41, "Score": 0.8710513114929199, "Text": "pulmonary embolism", "Category": "MEDICAL_CONDITION", "Type": "DX_NAME", "Traits": [{"Name": "DIAGNOSIS", "Score": 0.9528505802154541}]}, {"Id": 3, "BeginOffset": 50, "EndOffset": 55, "Score": 0.8708893060684204, "Text": "acute", "Category": "MEDICAL_CONDITION", "Type": "ACUITY", "Traits": []}, {"Id": 5, "BeginOffset": 56, "EndOffset": 59, "Score": 0.5284059047698975, "Text": "cor", "Category": "ANATOMY", "Type": "SYSTEM_ORGAN_SITE", "Traits": []}], "UnmappedAttributes": [], "ResponseMetadata": {"RequestId": "ce3c6895-0454-11e9-94cb-17a781f62a47", "HTTPStatusCode": 200, "HTTPHeaders": {"content-type": "application/x-amz-json-1.1", "date": "Thu, 20 Dec 2018 12:43:09 GMT", "x-amzn-requestid": "ce3c6895-0454-11e9-94cb-17a781f62a47", "content-length": "1007", "connection": "keep-alive"}, "RetryAttempts": 0}}