{"Entities": [{"Id": 2, "BeginOffset": 0, "EndOffset": 3, "Score": 0.9401130676269531, "Text": "ear", "Category": "ANATOMY", "Type": "SYSTEM_ORGAN_SITE", "Traits": []}, {"Id": 0, "BeginOffset": 0, "EndOffset": 8, "Score": 0.8414236903190613, "Text": "ear pain", "Category": "MEDICAL_CONDITION", "Type": "DX_NAME", "Traits": [{"Name": "SYMPTOM", "Score": 0.47111615538597107}]}, {"Id": 1, "BeginOffset": 9, "EndOffset": 16, "Score": 0.8543126583099365, "Text": "otalgia", "Category": "MEDICAL_CONDITION", "Type": "DX_NAME", "Traits": [{"Name": "SYMPTOM", "Score": 0.48102837800979614}]}], "UnmappedAttributes": [], "ResponseMetadata": {"RequestId": "d0f08c1d-0454-11e9-94cb-17a781f62a47", "HTTPStatusCode": 200, "HTTPHeaders": {"content-type": "application/x-amz-json-1.1", "date": "Thu, 20 Dec 2018 12:43:14 GMT", "x-amzn-requestid": "d0f08c1d-0454-11e9-94cb-17a781f62a47", "content-length": "557", "connection": "keep-alive"}, "RetryAttempts": 0}}