{"Entities": [{"Id": 0, "BeginOffset": 0, "EndOffset": 8, "Score": 0.7778853178024292, "Text": "headache", "Category": "MEDICAL_CONDITION", "Type": "DX_NAME", "Traits": []}, {"Id": 1, "BeginOffset": 9, "EndOffset": 17, "Score": 0.883475124835968, "Text": "vomiting", "Category": "MEDICAL_CONDITION", "Type": "DX_NAME", "Traits": []}], "UnmappedAttributes": [], "ResponseMetadata": {"RequestId": "8ff97d06-0414-11e9-94cb-17a781f62a47", "HTTPStatusCode": 200, "HTTPHeaders": {"content-type": "application/x-amz-json-1.1", "date": "Thu, 20 Dec 2018 05:03:17 GMT", "x-amzn-requestid": "8ff97d06-0414-11e9-94cb-17a781f62a47", "content-length": "326", "connection": "keep-alive"}, "RetryAttempts": 0}}