{"Entities": [{"Id": 0, "BeginOffset": 0, "EndOffset": 15, "Score": 0.8911266326904297, "Text": "facial fracture", "Category": "MEDICAL_CONDITION", "Type": "DX_NAME", "Traits": [{"Name": "DIAGNOSIS", "Score": 0.9298158288002014}]}], "UnmappedAttributes": [], "ResponseMetadata": {"RequestId": "76526344-0456-11e9-82d8-a57ca857a891", "HTTPStatusCode": 200, "HTTPHeaders": {"content-type": "application/x-amz-json-1.1", "date": "Thu, 20 Dec 2018 12:55:01 GMT", "x-amzn-requestid": "76526344-0456-11e9-82d8-a57ca857a891", "content-length": "237", "connection": "keep-alive"}, "RetryAttempts": 1}}