{"Entities": [{"Id": 0, "BeginOffset": 7, "EndOffset": 10, "Score": 0.3169478476047516, "Text": "ems", "Category": "PROTECTED_HEALTH_INFORMATION", "Type": "ADDRESS", "Traits": []}], "UnmappedAttributes": [], "ResponseMetadata": {"RequestId": "8b7accf5-0456-11e9-be2d-0757d81fd362", "HTTPStatusCode": 200, "HTTPHeaders": {"content-type": "application/x-amz-json-1.1", "date": "Thu, 20 Dec 2018 12:55:36 GMT", "x-amzn-requestid": "8b7accf5-0456-11e9-be2d-0757d81fd362", "content-length": "189", "connection": "keep-alive"}, "RetryAttempts": 0}}