{"Entities": [{"Id": 0, "BeginOffset": 0, "EndOffset": 8, "Score": 0.8511502742767334, "Text": "fracture", "Category": "MEDICAL_CONDITION", "Type": "DX_NAME", "Traits": [{"Name": "DIAGNOSIS", "Score": 0.8930984735488892}]}, {"Id": 2, "BeginOffset": 32, "EndOffset": 36, "Score": 0.9764707088470459, "Text": "head", "Category": "ANATOMY", "Type": "SYSTEM_ORGAN_SITE", "Traits": []}, {"Id": 1, "BeginOffset": 59, "EndOffset": 74, "Score": 0.5990077257156372, "Text": "closed fracture", "Category": "MEDICAL_CONDITION", "Type": "DX_NAME", "Traits": [{"Name": "DIAGNOSIS", "Score": 0.9632090926170349}]}], "UnmappedAttributes": [], "ResponseMetadata": {"RequestId": "bf308fe8-0456-11e9-994f-894fdeb1b4a9", "HTTPStatusCode": 200, "HTTPHeaders": {"content-type": "application/x-amz-json-1.1", "date": "Thu, 20 Dec 2018 12:57:02 GMT", "x-amzn-requestid": "bf308fe8-0456-11e9-994f-894fdeb1b4a9", "content-length": "571", "connection": "keep-alive"}, "RetryAttempts": 0}}