{"Entities": [{"Id": 0, "BeginOffset": 11, "EndOffset": 26, "Score": 0.8180971741676331, "Text": "testicular pain", "Category": "MEDICAL_CONDITION", "Type": "DX_NAME", "Traits": [{"Name": "SYMPTOM", "Score": 0.5729122161865234}]}], "UnmappedAttributes": [], "ResponseMetadata": {"RequestId": "80290b97-0457-11e9-94cb-17a781f62a47", "HTTPStatusCode": 200, "HTTPHeaders": {"content-type": "application/x-amz-json-1.1", "date": "Thu, 20 Dec 2018 13:02:27 GMT", "x-amzn-requestid": "80290b97-0457-11e9-94cb-17a781f62a47", "content-length": "236", "connection": "keep-alive"}, "RetryAttempts": 0}}