{"Entities": [{"Id": 0, "BeginOffset": 0, "EndOffset": 12, "Score": 0.9897484183311462, "Text": "constipation", "Category": "MEDICAL_CONDITION", "Type": "DX_NAME", "Traits": [{"Name": "SYMPTOM", "Score": 0.4064371585845947}]}], "UnmappedAttributes": [], "ResponseMetadata": {"RequestId": "b50d62e2-0457-11e9-82d8-a57ca857a891", "HTTPStatusCode": 200, "HTTPHeaders": {"content-type": "application/x-amz-json-1.1", "date": "Thu, 20 Dec 2018 13:03:54 GMT", "x-amzn-requestid": "b50d62e2-0457-11e9-82d8-a57ca857a891", "content-length": "232", "connection": "keep-alive"}, "RetryAttempts": 0}}