{"Entities": [{"Id": 0, "BeginOffset": 0, "EndOffset": 15, "Score": 0.8009194731712341, "Text": "assault assault", "Category": "MEDICAL_CONDITION", "Type": "DX_NAME", "Traits": [{"Name": "DIAGNOSIS", "Score": 0.910016655921936}]}], "UnmappedAttributes": [], "ResponseMetadata": {"RequestId": "8424ad37-0458-11e9-994f-894fdeb1b4a9", "HTTPStatusCode": 200, "HTTPHeaders": {"content-type": "application/x-amz-json-1.1", "date": "Thu, 20 Dec 2018 13:09:43 GMT", "x-amzn-requestid": "8424ad37-0458-11e9-994f-894fdeb1b4a9", "content-length": "236", "connection": "keep-alive"}, "RetryAttempts": 0}}