{"Entities": [{"Id": 0, "BeginOffset": 17, "EndOffset": 21, "Score": 0.9842984676361084, "Text": "pain", "Category": "MEDICAL_CONDITION", "Type": "DX_NAME", "Traits": [{"Name": "SYMPTOM", "Score": 0.6690580248832703}]}], "UnmappedAttributes": [], "ResponseMetadata": {"RequestId": "5d3f629d-0415-11e9-9cad-8715dd21eb24", "HTTPStatusCode": 200, "HTTPHeaders": {"content-type": "application/x-amz-json-1.1", "date": "Thu, 20 Dec 2018 05:09:01 GMT", "x-amzn-requestid": "5d3f629d-0415-11e9-9cad-8715dd21eb24", "content-length": "225", "connection": "keep-alive"}, "RetryAttempts": 0}}