{"Entities": [{"Id": 0, "BeginOffset": 0, "EndOffset": 11, "Score": 0.9318053126335144, "Text": "insect bite", "Category": "MEDICAL_CONDITION", "Type": "DX_NAME", "Traits": [{"Name": "DIAGNOSIS", "Score": 0.8248527646064758}]}], "UnmappedAttributes": [], "ResponseMetadata": {"RequestId": "6b45f82d-0416-11e9-be2d-0757d81fd362", "HTTPStatusCode": 200, "HTTPHeaders": {"content-type": "application/x-amz-json-1.1", "date": "Thu, 20 Dec 2018 05:16:34 GMT", "x-amzn-requestid": "6b45f82d-0416-11e9-be2d-0757d81fd362", "content-length": "233", "connection": "keep-alive"}, "RetryAttempts": 1}}